RW/__init__.py
RW/CLI/CLI.py
RW/CLI/__init__.py
RW/CLI/cli_utils.py
RW/CLI/json_parser.py
RW/CLI/local_process.py
RW/CLI/postgres_helper.py
RW/CLI/stdout_parser.py
RW/K8sApplications/__init__.py
RW/K8sApplications/_test_parsers.py
RW/K8sApplications/k8s_applications.py
RW/K8sApplications/migrations_inspector.py
RW/K8sApplications/no_stacktraces_report.jinja2
RW/K8sApplications/parsers.py
RW/K8sApplications/repository.py
RW/K8sApplications/simple_stacktrace_report.jinja2
RW/K8sApplications/test.sh
RW/K8sApplications/test_data/djangojson.log
RW/K8sApplications/test_data/golang.log
RW/K8sApplications/test_data/java.log
RW/K8sApplications/test_data/node.log
RW/K8sApplications/test_data/python.log
RW/K8sHelper/__init__.py
RW/K8sHelper/k8s_helper.py
RW/NextSteps/Suggest.py
RW/NextSteps/__init__.py
RW/NextSteps/Kubernetes/mapping.yaml
runwhen_cli_keywords-0.0.15.dist-info/LICENSE
runwhen_cli_keywords-0.0.15.dist-info/METADATA
runwhen_cli_keywords-0.0.15.dist-info/WHEEL
runwhen_cli_keywords-0.0.15.dist-info/top_level.txt
runwhen_cli_keywords-0.0.15.dist-info/RECORD
