Metadata-Version: 2.1
Name: runwhen-cli-keywords
Version: 0.0.15
Summary: A set of RunWhen published CLI keywords and python libraries for interacting with APIs using CLIs
Home-page: https://github.com/runwhen-contrib/rw-cli-codecollection
Author: Kyle Forster
Author-email: kyle.forster@runwhen.com
License: Apache License 2.0
Platform: UNKNOWN
Classifier: Programming Language :: Python :: 3
Classifier: License :: OSI Approved :: Apache Software License
License-File: LICENSE
Requires-Dist: jinja2 (==3.1.4)
Requires-Dist: jmespath (>=1.0.1)
Requires-Dist: python-dateutil (==2.8.2)
Requires-Dist: pyyaml (==6.0.1)
Requires-Dist: requests (>=2.31.0)
Requires-Dist: robotframework (>=4.1.2)
Requires-Dist: thefuzz (==0.20.0)
